p6/__init__.py
p6/fmt64.py
p6/hello.py
p6-0.1.5.dist-info/LICENSE
p6-0.1.5.dist-info/METADATA
p6-0.1.5.dist-info/WHEEL
p6-0.1.5.dist-info/top_level.txt
p6-0.1.5.dist-info/RECORD
