Metadata-Version: 2.1
Name: p6
Version: 0.1.5
Summary: module by posix
Home-page: http://p6.is
Author: posix1
Author-email: posix.lee@gmail.com
License: MIT
Platform: UNKNOWN
Classifier: Programming Language :: Python :: 3
Classifier: License :: OSI Approved :: MIT License
Classifier: Operating System :: OS Independent
